{
  "generatedAt": "2026-06-30T20:13:46.084Z",
  "source": "static-refresh",
  "sourcePolicy": "Herbalisti allowlist: public research APIs and independent longevity sources; Big Pharma names filtered from source/title metadata.",
  "latestRefresh": {
    "id": "static-refresh-20260630T201346084Z",
    "triggerType": "static-refresh",
    "status": "completed",
    "startedAt": "2026-06-30T20:13:46.084Z",
    "finishedAt": "2026-06-30T20:13:46.084Z",
    "itemCount": 24,
    "persistedCount": 0,
    "publicItemCount": 24,
    "warningCount": 0,
    "warnings": [],
    "sourcePolicy": "Herbalisti allowlist: public research APIs and independent longevity sources; Big Pharma names filtered from source/title metadata."
  },
  "publicSnapshot": {
    "status": "updated",
    "itemCount": 24,
    "generatedAt": "2026-06-30T20:13:46.084Z"
  }
}
